LICENSE
README.md
setup.py
bin/forcephoto.py
ztflc/__init__.py
ztflc/diffdata.py
ztflc/fitter.py
ztflc/forcephotometry.py
ztflc/io.py
ztflc/utils.py
ztflc.egg-info/PKG-INFO
ztflc.egg-info/SOURCES.txt
ztflc.egg-info/dependency_links.txt
ztflc.egg-info/top_level.txt