Metadata-Version: 2.1
Name: ztflc
Version: 0.2.10
Summary: ztflc: Force photometry lc fitter
Home-page: https://github.com/MickaelRigault/ztflc/
Download-URL: https://github.com/MickaelRigault/ztflc/tarball/0.2
Author: Mickael Rigault
Author-email: m.rigault@ipnl.in2p3.fr
Maintainer: Mickael Rigault
Maintainer-email: m.rigault@ipnl.in2p3.fr
License: BSD (3-clause)
Classifier: Intended Audience :: Science/Research
Classifier: Programming Language :: Python :: 2.7
Classifier: Programming Language :: Python :: 3.5
Classifier: License :: OSI Approved :: BSD License
Classifier: Topic :: Scientific/Engineering :: Astronomy
Classifier: Operating System :: POSIX
Classifier: Operating System :: Unix
Classifier: Operating System :: MacOS
License-File: LICENSE
